MANIFEST.in
README.md
setup.py
IntentIdentification/__init__.py
IntentIdentification/dataset.pkl
IntentIdentification/intent_dict.txt
IntentIdentification/intent_list.txt
IntentIdentification/model.pt
IntentIdentification/predict.py
IntentIdentification/word_dict.txt
IntentIdentification/word_list.txt
IntentIdentification.egg-info/PKG-INFO
IntentIdentification.egg-info/SOURCES.txt
IntentIdentification.egg-info/dependency_links.txt
IntentIdentification.egg-info/requires.txt
IntentIdentification.egg-info/top_level.txt
IntentIdentification/utils/loader.py
IntentIdentification/utils/module.py
IntentIdentification/utils/predict_process.py