Metadata-Version: 2.1
Name: IntentIdentification
Version: 0.0.1
Summary: A package to detect intent from utterances.
Home-page: https://gitlab.com/AlphaDino/commercebot/-/tree/master/Direct%20Contact%20Intent%20Detection
Author: Shreyansh Das
Author-email: shreyanshdas00@gmail.com
License: UNKNOWN
Platform: UNKNOWN
Classifier: Programming Language :: Python :: 3
Classifier: License :: OSI Approved :: MIT License
Classifier: Operating System :: OS Independent
Requires-Python: >=3.6
